pyflichub/__init__.py
pyflichub/button.py
pyflichub/client.py
pyflichub/command.py
pyflichub/event.py
pyflichub/flichub.py
pyflichub/server_command.py
pyflichub/server_info.py
pyflichub/version.py
pyflichub_tcpclient-0.1.10.dist-info/LICENSE
pyflichub_tcpclient-0.1.10.dist-info/METADATA
pyflichub_tcpclient-0.1.10.dist-info/WHEEL
pyflichub_tcpclient-0.1.10.dist-info/top_level.txt
pyflichub_tcpclient-0.1.10.dist-info/RECORD
