Metadata-Version: 2.1
Name: pyflichub-tcpclient
Version: 0.1.10
Summary: Asynchronous Python TCP Client for FlicHub
Home-page: https://github.com/JohNan/pyflichub-tcpclient
Author: Johan Nenzén
Author-email: johan.nanzen@gmail.com
License: MIT
Project-URL: Bug Tracker, https://github.com/JohNan/pyflichub-tcpclient/issues
Classifier: Framework :: AsyncIO
Classifier: Programming Language :: Python :: 3
Classifier: License :: OSI Approved :: MIT License
Classifier: Operating System :: OS Independent
Classifier: Topic :: Software Development :: Libraries :: Python Modules
Requires-Python: >=3.7
License-File: LICENSE
Requires-Dist: pyhumps
Requires-Dist: async-timeout
